pydash/__init__.py
tests/__init__.py
tests/test_string.py
pydash_ione03-1.0.1.dist-info/LICENSE
pydash_ione03-1.0.1.dist-info/METADATA
pydash_ione03-1.0.1.dist-info/WHEEL
pydash_ione03-1.0.1.dist-info/top_level.txt
pydash_ione03-1.0.1.dist-info/RECORD
