Metadata-Version: 2.1
Name: pydash-ione03
Version: 1.0.1
Summary: A small clone of lodash
Home-page: https://github.com/ione03/pydash
Author-email: suratiwan03@gmail.com
License: UNKNOWN
Keywords: lodash,string,manipulation
Platform: UNKNOWN
Classifier: License :: OSI Approved :: MIT License
Classifier: Intended Audience :: Developers
Classifier: Programming Language :: Python :: 3 :: Only
